{
  "id": 269,
  "name": "syncTriggerDirect",
  "type": "JAVASCRIPT",
  "description": "Trigger direto de sync com Movidesk — retorna resultado detalhado com logs de request/response",
  "code": "\n// Direct sync trigger — called from frontend\n// event.mode = 'INCREMENTAL' | 'FULL'\n// event.token = Movidesk API token\n// event.lastSync = last sync date (ISO string)\n// event.startDate = optional start date filter\n// event.pageSize = tickets per page (default 50)\n// event.maxPages = max pages to fetch (safety limit)\n\nconst MOVIDESK_URL = 'https://api.movidesk.com/public/v1';\nconst mode = (event.mode || 'INCREMENTAL').toUpperCase();\nconst token = event.token || '';\nconst lastSync = event.lastSync || '';\nconst startDate = event.startDate || '';\nconst pageSize = parseInt(event.pageSize) || 50;\nconst maxPages = parseInt(event.maxPages) || 200;\nconst session = 'S' + Date.now().toString(36).toUpperCase();\n\nif (!token) {\n  return { success: false, error: 'Token Movidesk nao configurado', session };\n}\n\nconst selectFields = 'id,protocol,type,subject,category,urgency,status,baseStatus,origin,createdDate,ownerTeam,serviceFirstLevel,lastUpdate,actionCount,lifeTimeWorkingTime,resolvedIn,closedIn,canceledIn,lastActionDate,slaAgreement,slaAgreementRule,slaSolutionTime,slaResponseTime';\n\nconst results = [];\nlet totalTickets = 0;\nlet totalErrors = 0;\nlet currentEndpoint = '';\n\nasync function fetchPage(endpoint, orderBy, filterParam, label, page) {\n  const skip = page * pageSize;\n  const url = MOVIDESK_URL + '/' + endpoint + '?token=' + token + '&$top=' + pageSize + '&$skip=' + skip + '&$select=' + selectFields + '&$orderby=' + orderBy + (filterParam || '');\n\n  // Mask token in logged URL\n  const logUrl = url.replace(token, token.substring(0, 4) + '****' + token.substring(token.length - 4));\n\n  const start = Date.now();\n  let responseCode = 0;\n  let responseBody = '';\n  let ticketsCount = 0;\n  let error = '';\n\n  try {\n    const res = await fetch(url, { signal: AbortSignal.timeout(120000) });\n    responseCode = res.status;\n    const elapsed = Date.now() - start;\n\n    if (res.status === 429) {\n      const retryAfter = parseInt(res.headers.get('retry-after') || '60');\n      error = 'Rate limit (429). Retry-After: ' + retryAfter + 's';\n      responseBody = 'Rate limited. Aguardar ' + retryAfter + 's antes de tentar novamente.';\n      results.push({ page, label, responseCode, ticketsCount: 0, error, elapsed });\n      return { ok: false, retryAfter, tickets: [] };\n    }\n\n    if (res.status === 403) {\n      const body = await res.text();\n      error = 'HTTP 403 Forbidden — token invalido ou sem permissao';\n      responseBody = body.substring(0, 500);\n      results.push({ page, label, responseCode, ticketsCount: 0, error, elapsed });\n      return { ok: false, fatal: true, tickets: [] };\n    }\n\n    if (!res.ok) {\n      const body = await res.text();\n      error = 'HTTP ' + res.status;\n      responseBody = body.substring(0, 500);\n      results.push({ page, label, responseCode, ticketsCount: 0, error, elapsed });\n      return { ok: false, tickets: [] };\n    }\n\n    const tickets = await res.json();\n    if (!Array.isArray(tickets)) {\n      error = 'Resposta nao e array';\n      responseBody = JSON.stringify(tickets).substring(0, 500);\n      results.push({ page, label, responseCode, ticketsCount: 0, error, elapsed });\n      return { ok: true, tickets: [] };\n    }\n\n    ticketsCount = tickets.length;\n    responseBody = 'OK: ' + ticketsCount + ' tickets retornados';\n    results.push({ page, label, responseCode, ticketsCount, error: '', elapsed });\n\n    return { ok: true, tickets };\n  } catch (e) {\n    error = String(e.message || e).substring(0, 300);\n    results.push({ page, label, responseCode: 0, ticketsCount: 0, error, elapsed: Date.now() - start });\n    return { ok: false, tickets: [] };\n  }\n}\n\n// Determine sync strategy\nconst isFullSync = mode === 'FULL' || !lastSync;\nlet filterParam = '';\n\nif (!isFullSync && lastSync) {\n  // Incremental: filter by lastUpdate > lastSync - 2min\n  const d = new Date(lastSync);\n  d.setMinutes(d.getMinutes() - 2);\n  filterParam = '&$filter=lastUpdate ge ' + d.toISOString().slice(0, 19) + 'z';\n} else if (startDate) {\n  filterParam = '&$filter=lastUpdate ge ' + startDate + 'T00:00:00z';\n}\n\n// Fetch tickets\nconst endpoints = isFullSync\n  ? [\n      { endpoint: 'tickets/past', orderBy: 'id asc', label: 'FULL_PAST' },\n      { endpoint: 'tickets', orderBy: 'lastUpdate asc', label: 'FULL_RECENT' }\n    ]\n  : [\n      { endpoint: 'tickets', orderBy: 'lastUpdate asc', label: 'INCREMENTAL' }\n    ];\n\nlet fatalError = false;\nconst ticketIds = [];\n\nfor (const ep of endpoints) {\n  if (fatalError) break;\n  currentEndpoint = ep.endpoint;\n\n  for (let page = 0; page < maxPages; page++) {\n    const result = await fetchPage(ep.endpoint, ep.orderBy, filterParam, ep.label, page);\n\n    if (result.fatal) {\n      fatalError = true;\n      totalErrors++;\n      break;\n    }\n\n    if (result.retryAfter) {\n      // We can't wait long in a SF — return partial results\n      totalErrors++;\n      break;\n    }\n\n    if (!result.ok) {\n      totalErrors++;\n      if (totalErrors >= 3) break;\n      continue;\n    }\n\n    if (result.tickets.length === 0) break;\n\n    totalTickets += result.tickets.length;\n    for (const t of result.tickets) {\n      ticketIds.push(t.id);\n    }\n\n    if (result.tickets.length < pageSize) break;\n\n    // Delay between pages to respect rate limit (6s = 10 req/min)\n    await new Promise(r => setTimeout(r, 6500));\n  }\n}\n\nreturn {\n  success: !fatalError,\n  session,\n  mode: isFullSync ? 'FULL' : 'INCREMENTAL',\n  totalTickets,\n  totalErrors,\n  totalRequests: results.length,\n  endpoint: currentEndpoint,\n  requests: results,\n  ticketIdsSample: ticketIds.slice(0, 20),\n  filterParam: filterParam || '(none)',\n  message: fatalError\n    ? 'Sync falhou com erro fatal (verifique token e permissoes)'\n    : (totalTickets > 0 ? totalTickets + ' tickets encontrados' : 'Nenhum ticket novo encontrado')\n};\n",
  "createdBy": "leandro.moreira@neuonsolucoes.com",
  "createdAt": "2026-03-08T21:07:10",
  "updatedAt": "2026-03-08T21:07:10"
}